smart_augmentation/__init__.py
smart_augmentation/color.py
smart_augmentation/geometric.py
smart_augmentation/noise.py
smart_augmentation/occlusion.py
smart_augmentation/utils.py
smart_augmentation/video.py
smart_augmentation-0.2.3.dist-info/METADATA
smart_augmentation-0.2.3.dist-info/WHEEL
smart_augmentation-0.2.3.dist-info/top_level.txt
smart_augmentation-0.2.3.dist-info/RECORD
