Metadata-Version: 2.4
Name: smart_augmentation
Version: 0.2.3
Summary: Comprehensive image and video data augmentation library with recommendations, geometric, color, noise, and occlusion techniques
Home-page: https://github.com/divinegupta0611/Data_Augmentation
Author: Divine Gupta
Author-email: guptadivine0611@gmail.com
Classifier: Development Status :: 4 - Beta
Classifier: Intended Audience :: Developers
Classifier: License :: OSI Approved :: MIT License
Classifier: Programming Language :: Python :: 3
Classifier: Topic :: Scientific/Engineering :: Artificial Intelligence
Requires-Python: >=3.7
Dynamic: author
Dynamic: author-email
Dynamic: classifier
Dynamic: description
Dynamic: description-content-type
Dynamic: home-page
Dynamic: requires-python
Dynamic: summary
